leejPack/encode.py
leejPack/npm.py
leejPack-0.0.1.dist-info/LICENSE
leejPack-0.0.1.dist-info/METADATA
leejPack-0.0.1.dist-info/WHEEL
leejPack-0.0.1.dist-info/top_level.txt
leejPack-0.0.1.dist-info/RECORD
